{
  "levelsFlow": "async",
  "tasksFlow": "async",
  "name": "root",
  "delay": 300,
  "levels": [
    {
      "levelsFlow": "async",
      "tasksFlow": "sync",
      "delay": 5000,
      "name": "root-level1",
      "levels": [],
      "tasks": [
        {
          "name": "root-level1-task1",
          "actionsFlow": "async",
          "delay": 1000,
          "actions": [
            {
              "name": "root-level1-task1-action1",
              "type": "log",
              "message": "root-level1-task1-action1"
            },
            {
              "name": "root-level1-task1-action2",
              "type": "log",
              "message": "root-level1-task1-action2"
            }
          ]
        },
        {
          "name": "root-level2-task2",
          "actionsFlow": "async",
          "delay": 3500,
          "actions": []
        }
      ]
    }
  ],
  "tasks": []
}
